{
	"company": "Huntsman",
	"name": "",
	"id": 1613046133295,
	"questions": [
		{
			"text": "",
			"type": 2,
			"scoreImpact": 0,
			"image": "/uploads/Huntsman/file-1-2-1613046133372.png",
			"activePoints": [],
			"answers": [
				{
					"text": "",
					"correct": "",
					"coordinates": {
						"x": 3.4420289855072466,
						"y": 37.16551040634292
					},
					"size": {
						"width": 0,
						"height": 0
					},
					"order": "",
					"partnerId": "",
					"image": ""
				}
			]
		},
		{
			"text": "",
			"type": 2,
			"scoreImpact": 0,
			"image": "/uploads/Huntsman/file-2-2-1613046133385.png",
			"activePoints": [],
			"answers": [
				{
					"text": "",
					"correct": "",
					"coordinates": {
						"x": 39.67391304347826,
						"y": 3.1714568880079286
					},
					"size": {
						"width": 24.27536231884058,
						"height": 13.280475718533202
					},
					"order": "",
					"partnerId": "",
					"image": ""
				},
				{
					"text": "",
					"correct": "",
					"coordinates": {
						"x": 65.57971014492753,
						"y": 19.821605550049554
					},
					"size": {
						"width": 24.094202898550723,
						"height": 13.181367690782952
					},
					"order": "",
					"partnerId": "",
					"image": ""
				}
			]
		}
	],
	"filename": 1613046133415
}